skillhub/__init__.py
skillhub/cli.py
skillhub/commands/__init__.py
skillhub/core/__init__.py
skillhub/core/config.py
skillhub/core/registry.py
skillhub/core/validator.py
skillhub/utils/__init__.py
skillhub-0.1.0.dist-info/METADATA
skillhub-0.1.0.dist-info/WHEEL
skillhub-0.1.0.dist-info/entry_points.txt
skillhub-0.1.0.dist-info/top_level.txt
skillhub-0.1.0.dist-info/RECORD
