Metadata-Version: 2.4
Name: skillhub
Version: 0.1.0
Summary: Package manager for AI agent workflows
Home-page: https://github.com/v1k22/skillhub-cli
Author: Bhavik Dhandhala
Author-email: dhandhalyabhavik@gmail.com
Project-URL: Bug Reports, https://github.com/v1k22/skillhub-cli/issues
Project-URL: Source, https://github.com/v1k22/skillhub-cli
Project-URL: Registry, https://github.com/v1k22/skillhub-registry
Keywords: ai agent automation workflow package-manager
Classifier: Development Status :: 3 - Alpha
Classifier: Intended Audience :: Developers
Classifier: Topic :: Software Development :: Build Tools
Classifier: License :: OSI Approved :: MIT License
Classifier: Programming Language :: Python :: 3
Classifier: Programming Language :: Python :: 3.9
Classifier: Programming Language :: Python :: 3.10
Classifier: Programming Language :: Python :: 3.11
Classifier: Programming Language :: Python :: 3.12
Requires-Python: >=3.9
Requires-Dist: click>=8.0.0
Requires-Dist: requests>=2.28.0
Requires-Dist: pyyaml>=6.0
Requires-Dist: rich>=13.0.0
Dynamic: author
Dynamic: author-email
Dynamic: classifier
Dynamic: description
Dynamic: description-content-type
Dynamic: home-page
Dynamic: keywords
Dynamic: project-url
Dynamic: requires-dist
Dynamic: requires-python
Dynamic: summary
